haystack_integrations/components/embedders/google_vertex/__init__.py
haystack_integrations/components/embedders/google_vertex/document_embedder.py
haystack_integrations/components/embedders/google_vertex/text_embedder.py
haystack_integrations/components/generators/google_vertex/__init__.py
haystack_integrations/components/generators/google_vertex/captioner.py
haystack_integrations/components/generators/google_vertex/code_generator.py
haystack_integrations/components/generators/google_vertex/gemini.py
haystack_integrations/components/generators/google_vertex/image_generator.py
haystack_integrations/components/generators/google_vertex/question_answering.py
haystack_integrations/components/generators/google_vertex/text_generator.py
haystack_integrations/components/generators/google_vertex/chat/__init__.py
haystack_integrations/components/generators/google_vertex/chat/gemini.py
google_vertex_haystack-5.3.0.post1.dist-info/METADATA
google_vertex_haystack-5.3.0.post1.dist-info/WHEEL
google_vertex_haystack-5.3.0.post1.dist-info/licenses/LICENSE.txt
google_vertex_haystack-5.3.0.post1.dist-info/RECORD
